dexus_vault/__init__.py
dexus_vault/__main__.py
dexus_vault/__version__.py
dexus_vault/syncer.py
dexus_vault/grpc_dexidp/__init__.py
dexus_vault/grpc_dexidp/dexidp/__init__.py
dexus_vault/grpc_dexidp/dexidp/api_pb2.py
dexus_vault/grpc_dexidp/dexidp/api_pb2_grpc.py
dexus_vault/src/__init__.py
dexus_vault/src/dex_processor.py
dexus_vault/src/vault_processor.py
dexus_vault/utils/__init__.py
dexus_vault/utils/config.py
dexus_vault/utils/logger.py
dexus_vault/utils/metrics.py
dexus_vault-0.3.1.dist-info/LICENSE
dexus_vault-0.3.1.dist-info/METADATA
dexus_vault-0.3.1.dist-info/WHEEL
dexus_vault-0.3.1.dist-info/entry_points.txt
dexus_vault-0.3.1.dist-info/top_level.txt
dexus_vault-0.3.1.dist-info/RECORD
