Metadata-Version: 2.1
Name: dexus-vault
Version: 0.3.1
Summary: Synchronizer of Dex clients with secrets in Vault
Home-page: https://github.com/ifurs/dexus-vault
Author: ifurs
License: Apache License 2.0
Project-URL: Source, https://github.com/ifurs/dexus-vault
Classifier: License :: OSI Approved :: Apache Software License
Classifier: Programming Language :: Python
Classifier: Programming Language :: Python :: 3
Classifier: Programming Language :: Python :: 3.8
Classifier: Programming Language :: Python :: 3.9
Classifier: Programming Language :: Python :: 3.10
Classifier: Programming Language :: Python :: 3.11
Classifier: Programming Language :: Python :: 3.12
Classifier: Programming Language :: Python :: Implementation :: CPython
Classifier: Operating System :: OS Independent
Requires-Python: >=3.8
License-File: LICENSE
Requires-Dist: grpcio ~=1.62.0
Requires-Dist: grpcio-tools ~=1.60.1
Requires-Dist: googleapis-common-protos >=1.62.0
Requires-Dist: protobuf ~=4.25.3
Requires-Dist: hvac ~=2.1.0
Requires-Dist: prometheus-client ~=0.20.0
Requires-Dist: pydantic-settings ~=2.2.1
Requires-Dist: pydantic >=2.7.0
